{
  "hints": [],
  "groups": [
    {
      "sourceType": "pers.ljy.background.datasource.DataSourceConfiguration",
      "name": "druid.master",
      "sourceMethod": "public javax.sql.DataSource masterDataSource() ",
      "type": "javax.sql.DataSource"
    },
    {
      "sourceType": "pers.ljy.background.datasource.DataSourceConfiguration",
      "name": "druid.slaveOne",
      "sourceMethod": "public javax.sql.DataSource slaveDataSourceOne() ",
      "type": "javax.sql.DataSource"
    }
  ],
  "properties": []
}